calculator_demo_pkg/__init__.py
calculator_demo_pkg/scientific/__init__.py
calculator_demo_pkg/scientific/cos.py
calculator_demo_pkg/scientific/sin.py
calculator_demo_pkg/standard/__init__.py
calculator_demo_pkg/standard/add.py
calculator_demo_pkg/standard/divide.py
calculator_demo_pkg/standard/multiply.py
calculator_demo_pkg/standard/subtract.py
calculator_demo_pkg-0.0.4.dist-info/LICENSE
calculator_demo_pkg-0.0.4.dist-info/METADATA
calculator_demo_pkg-0.0.4.dist-info/WHEEL
calculator_demo_pkg-0.0.4.dist-info/top_level.txt
calculator_demo_pkg-0.0.4.dist-info/RECORD
